_FastHJ.cpython-37m-darwin.so
_cpputils.cpython-37m-darwin.so
_delaunay.cpython-37m-darwin.so
_delaunay_class.cpython-37m-darwin.so
_delaunay_class3.cpython-37m-darwin.so
_fast_geometry.cpython-37m-darwin.so
SeismicMesh/__about__.py
SeismicMesh/__init__.py
SeismicMesh/decomp/__init__.py
SeismicMesh/decomp/blocker.py
SeismicMesh/generation/__init__.py
SeismicMesh/generation/mesh_generator.py
SeismicMesh/generation/utils.py
SeismicMesh/generation/cpp/__init__.py
SeismicMesh/geometry/__init__.py
SeismicMesh/geometry/rotation.py
SeismicMesh/geometry/signed_distance_functions.py
SeismicMesh/geometry/utils.py
SeismicMesh/geometry/cpp/__init__.py
SeismicMesh/migration/__init__.py
SeismicMesh/migration/migration.py
SeismicMesh/migration/cpp/__init__.py
SeismicMesh/sizing/__init__.py
SeismicMesh/sizing/mesh_size_function.py
SeismicMesh/sizing/size_function.py
SeismicMesh/sizing/cpp/__init__.py
common/__init__.py
common/bspline.py
common/circle_arc.py
common/curve_loop.py
common/dummy.py
common/ellipse_arc.py
common/geometry.py
common/line.py
common/line_base.py
common/plane_surface.py
common/point.py
common/polygon.py
common/spline.py
common/surface.py
common/surface_loop.py
common/volume.py
geo/__init__.py
geo/geometry.py
occ/__init__.py
occ/ball.py
occ/boolean.py
occ/box.py
occ/cone.py
occ/cylinder.py
occ/disk.py
occ/geometry.py
occ/rectangle.py
occ/torus.py
occ/wedge.py
SeismicMesh-3.6.2.dist-info/LICENSE.txt
SeismicMesh-3.6.2.dist-info/METADATA
SeismicMesh-3.6.2.dist-info/WHEEL
SeismicMesh-3.6.2.dist-info/top_level.txt
SeismicMesh-3.6.2.dist-info/RECORD
