Metadata-Version: 2.1
Name: SeismicMesh
Version: 3.6.2
Summary: 2D/3D serial and parallel triangular mesh generation for seismology
Home-page: https://github.com/krober10nd/SeismicMesh
Author: Keith Roberts
License: GPL-3.0-or-later
Platform: UNKNOWN
Classifier: Development Status :: 4 - Beta
Classifier: License :: OSI Approved :: GNU General Public License v3 or later (GPLv3+)
Classifier: Operating System :: OS Independent
Classifier: Programming Language :: Python :: 3
Classifier: Programming Language :: Python :: 3.5
Classifier: Programming Language :: Python :: 3.6
Classifier: Programming Language :: Python :: 3.7
Classifier: Programming Language :: Python :: 3.8
Classifier: Programming Language :: Python :: 3.9
Classifier: Topic :: Scientific/Engineering
Classifier: Topic :: Scientific/Engineering :: Mathematics
Classifier: Topic :: Scientific/Engineering :: Physics
Classifier: Topic :: Scientific/Engineering :: Visualization
Requires-Python: >=3.0
Requires-Dist: numpy
Requires-Dist: segyio
Requires-Dist: scipy
Requires-Dist: meshio
Requires-Dist: h5py
Requires-Dist: matplotlib
Requires-Dist: mpi4py
Requires-Dist: pyamg
Requires-Dist: pytest-codeblocks
Provides-Extra: all
Requires-Dist: segyio ; extra == 'all'
Requires-Dist: meshplex ; extra == 'all'
Requires-Dist: pygalmesh ; extra == 'all'
Requires-Dist: pygmsh ; extra == 'all'
Requires-Dist: meshio ; extra == 'all'
Requires-Dist: termplotlib ; extra == 'all'
Provides-Extra: benchmarking
Requires-Dist: meshplex ; extra == 'benchmarking'
Requires-Dist: pygalmesh ; extra == 'benchmarking'
Requires-Dist: pygmsh ; extra == 'benchmarking'
Requires-Dist: meshio ; extra == 'benchmarking'
Requires-Dist: termplotlib ; extra == 'benchmarking'
Provides-Extra: io
Requires-Dist: segyio ; extra == 'io'
